CHANGES.rst
CONTRIBUTORS.rst
MANIFEST.in
README.rst
bootstrap.py
buildout.cfg
setup.py
docs/LICENSE.GPL
docs/LICENSE.rst
src/blog/__init__.py
src/blog.policy.egg-info/PKG-INFO
src/blog.policy.egg-info/SOURCES.txt
src/blog.policy.egg-info/dependency_links.txt
src/blog.policy.egg-info/entry_points.txt
src/blog.policy.egg-info/namespace_packages.txt
src/blog.policy.egg-info/not-zip-safe
src/blog.policy.egg-info/pbr.json
src/blog.policy.egg-info/requires.txt
src/blog.policy.egg-info/top_level.txt
src/blog/policy/__init__.py
src/blog/policy/configure.zcml
src/blog/policy/interfaces.py
src/blog/policy/setuphandlers.py
src/blog/policy/testing.py
src/blog/policy/testing.zcml
src/blog/policy/profiles/default/blogpolicy_marker.txt
src/blog/policy/profiles/default/browserlayer.xml
src/blog/policy/profiles/default/cssregistry.xml
src/blog/policy/profiles/default/metadata.xml
src/blog/policy/profiles/default/portlets.xml
src/blog/policy/profiles/default/propertiestool.xml
src/blog/policy/profiles/default/registry.xml
src/blog/policy/profiles/default/types/Folder.xml
src/blog/policy/profiles/testing/metadata.xml
src/blog/policy/static/.gitkeep
src/blog/policy/static/policy.css
src/blog/policy/tests/__init__.py
src/blog/policy/tests/test_robot.py
src/blog/policy/tests/test_setup.py
src/blog/policy/tests/robot/.gitkeep