Metadata-Version: 1.1
Name: blog.policy
Version: 0.1b8
Summary: A policy for blog suite
Home-page: https://github.com/IMIO/blog.policy
Author: bsuttor
Author-email: ben.suttor@gmail.com
License: GPL
Keywords: Plone Python Imio
Platform: UNKNOWN
Classifier: Environment :: Web Environment
Classifier: Framework :: Plone
Classifier: Framework :: Plone :: 4.3
Classifier: Programming Language :: Python
Classifier: Programming Language :: Python :: 2.7
